<annotation>
	<folder>images</folder>
	<filename>00097.jpg</filename>
	<path>/Users/josemanuel/Documents/Matia/initial_training_car/images/00097.jpg</path>
	<source>
		<database>Unknown</database>
	</source>
	<size>
		<width>78</width>
		<height>58</height>
		<depth>3</depth>
	</size>
	<segmented>0</segmented>
	<object>
		<name>car</name>
		<pose>Unspecified</pose>
		<truncated>0</truncated>
		<difficult>0</difficult>
		<bndbox>
			<xmin>3</xmin>
			<ymin>8</ymin>
			<xmax>74</xmax>
			<ymax>48</ymax>
		</bndbox>
	</object>
</annotation>
